virustotal_api_v2-0.8.dist-info/DESCRIPTION.rst
virustotal_api_v2-0.8.dist-info/METADATA
virustotal_api_v2-0.8.dist-info/RECORD
virustotal_api_v2-0.8.dist-info/WHEEL
virustotal_api_v2-0.8.dist-info/metadata.json
virustotal_api_v2-0.8.dist-info/top_level.txt
vt/__init__.py
