Metadata-Version: 2.0
Name: virustotal-api-v2
Version: 0.8
Summary: Python scripts to interact with the virustotal.com API
Home-page: https://github.com/nu11p0inter/virustotal
Author: Tal Melamed
Author-email: dev@appsec.it
License: GNU 3.0
Platform: UNKNOWN
Classifier: Programming Language :: Python :: 2.7
Classifier: License :: OSI Approved :: MIT License
Classifier: Operating System :: OS Independent
Requires-Dist: requests (>=2.2.1)
